data_scientist
