Metadata-Version: 1.0
Name: data-scientist
Version: 0.23
Summary: Fundamental tools for DS
Home-page: UNKNOWN
Author: 0100110101000001
Author-email: 0b0100110101000001@gmail.com
License: MIT
Platform: UNKNOWN
